{"name":"issue-expo-updates-42","slug":"issue-expo-updates-42","version":"1.0.19","sdkVersion":"42.0.0","platforms":["ios","android","web"],"currentFullName":"@anonymous/issue-expo-updates-42","originalFullName":"@anonymous/issue-expo-updates-42","locales":{},"bundledAssets":["asset_0bf88a8879166628020bb0dfdec73261.png"],"assetUrlOverride":"./assets","publishedTime":"2021-12-22T03:02:30.910Z","commitTime":"2021-12-22T03:02:30.910Z","releaseId":"34b1fd92-6987-46ad-9e0a-0b412cc9969d","revisionId":"v9a90JP7kO","id":"@anonymous/issue-expo-updates-42","platform":"android","bundleUrl":"https://babyking.github.io/expo_bundle/bundles/android-eb21bcd5f10e725a7da60d2f907e6489.js","dependencies":["expo","expo-splash-screen","expo-status-bar","expo-updates","react","react-dom","react-native","react-native-gesture-handler","react-native-reanimated","react-native-screens","react-native-unimodules","react-native-web"]}